Workbook
Name aporte: app!$C$9:$C$9
Name perfil_escolhido: app!$B$16:$B$16
Name rendimento_carteira: app!$C$5:$C$5
Name taxa_mensal: app!$C$11:$C$11
Name tempo_anos: app!$C$10:$C$10
Name valor_investido: app!$B$17:$B$17

Sheet app
A1: 🪙 FIINVEST🔹INTELIGÊNCIA & ALOCAÇÃO PATRIMONIAL
A3: ⚙️ CONFIGURAÇÕES OPERACIONAIS
A4: Salário | B4: ➔ | C4: 2000
A5: Rendimento Alvo da Carteira | B5: ➔ | C5: 0.006
A6: Sugestão de Investimento (30%) | B6: ➔ | C6: =C$4*30% -> 600
A8: 📈 SIMULADOR DE PATRIMÔNIO & RENDA RECORRENTE
A9: Aporte Mensal Pretendido | B9: ➔ | C9: 300
A10: Horizonte Temporal (Em Anos) | B10: ➔ | C10: 3
A11: Taxa de Rendimento Mensal Estimada | B11: ➔ | C11: 0.0108
A12: Patrimônio Líquido Acumulado | B12: ➔ | C12: {=FV(taxa_mensal, C10*12, aporte*-1)} -> 13114.933
A13: Renda Recorrente Mensal (Dividendos) | B13: ➔ | C13: {=C12*rendimento_carteira} -> 78.689595
A15: 📊 DIRECIONADOR DE ESTRATÉGIA & RISCO
A16: Perfil do Investidor (Selecione na Lista) ➔ | B16: Moderado
A17: VALOR A SER INVESTIDO POR MÊS | B17: =C9 -> 300
A19: TIPO DE FII | B19: Percentual Sugerido | C19: Valores
A20: TIJOLO | B20: {=VLOOKUP(perfil_escolhido & "-" & A20, apoio!$A:$D, 4, FALSE)} -> 0.3 | C20: {=B20 * valor_investido} -> 90
A21: PAPEL | B21: {=VLOOKUP(perfil_escolhido & "-" & A21, apoio!$A:$D, 4, FALSE)} -> 0.3 | C21: {=B21 * valor_investido} -> 90
A22: HÍBRIDO | B22: {=VLOOKUP(perfil_escolhido & "-" & A22, apoio!$A:$D, 4, FALSE)} -> 0.08 | C22: {=B22 * valor_investido} -> 24
A23: FOF | B23: {=VLOOKUP(perfil_escolhido & "-" & A23, apoio!$A:$D, 4, FALSE)} -> 0.08 | C23: {=B23 * valor_investido} -> 24
A24: MULTIESTRATÉGIA | B24: {=VLOOKUP(perfil_escolhido & "-" & A24, apoio!$A:$D, 4, FALSE)} -> 0.19 | C24: {=B24 * valor_investido} -> 57
A25: DESENVOLVIMENTO | B25: {=VLOOKUP(perfil_escolhido & "-" & A25, apoio!$A:$D, 4, FALSE)} -> 0.05 | C25: {=B25 * valor_investido} -> 15
A26: TOTAL | B26: =SUM(B$20:B$25) -> 1 | C26: =SUM(C$20:C$25) -> 300
A28: ⏳ SIMULADOR DE CENÁRIOS & RETROVISOR DO FUTURO
A29: Anos | B29: Projeção Patrimonial | C29: Dividendo Mensal Gerado
A30: 2 | B30: {=FV(taxa_mensal, A$30*12, aporte*-1)} -> 8169.2591 | C30: {=B$30 * rendimento_carteira} -> 49.015555
A31: 5 | B31: {=FV(taxa_mensal, A$31*12, aporte*-1)} -> 25141.206 | C31: {=B$31 * rendimento_carteira} -> 150.84723
A32: 10 | B32: {=FV(taxa_mensal, A$32*12, aporte*-1)} -> 73037.3 | C32: {=B$32 * rendimento_carteira} -> 438.2238
A33: 20 | B33: {=FV(taxa_mensal, A$33*12, aporte*-1)} -> 338114.7 | C33: {=B$33 * rendimento_carteira} -> 2028.6882
A34: 30 | B34: {=FV(taxa_mensal, A$34*12, aporte*-1)} -> 1300171.4 | C34: {=B$34 * rendimento_carteira} -> 7801.0287
A36: Preço da Cota do FII que você quer calcular ➔ | B36: 10
A38: Resultado do seu efeito bola de neve ➔ | B38: =IF(C13>=B36,"🎉 PARABÉNS! O seu ganho mensal já compra + " & INT(C13/B36) & " cotas sem mexer no seu salário.","⏳ QUASE LÁ! Ainda faltam R$ " & ROUND(B36-C13,2) & ". Continue assim! Logo o seu ganho mensal cobrirá o preço de uma cota.") -> 🎉 PARABÉNS! O seu ganho mensal já compra + 7 cotas sem mexer no seu salário.

Sheet apoio
A1: CHAVE | B1: PERFIL | C1: TIPO DE FII | D1: %
A2: =B2&"-"&C2 -> Conservador-TIJOLO | B2: Conservador | C2: TIJOLO | D2: 0.5
A3: =B3&"-"&C3 -> Conservador-PAPEL | B3: Conservador | C3: PAPEL | D3: 0.25
A4: =B4&"-"&C4 -> Conservador-HÍBRIDO | B4: Conservador | C4: HÍBRIDO | D4: 0.05
A5: =B5&"-"&C5 -> Conservador-FOF | B5: Conservador | C5: FOF | D5: 0.07
A6: =B6&"-"&C6 -> Conservador-MULTIESTRATÉGIA | B6: Conservador | C6: MULTIESTRATÉGIA | D6: 0.13
A7: =B7&"-"&C7 -> Conservador-DESENVOLVIMENTO | B7: Conservador | C7: DESENVOLVIMENTO | D7: 0
A8: =B8&"-"&C8 -> Moderado-TIJOLO | B8: Moderado | C8: TIJOLO | D8: 0.3
A9: =B9&"-"&C9 -> Moderado-PAPEL | B9: Moderado | C9: PAPEL | D9: 0.3
A10: =B10&"-"&C10 -> Moderado-HÍBRIDO | B10: Moderado | C10: HÍBRIDO | D10: 0.08
A11: =B11&"-"&C11 -> Moderado-FOF | B11: Moderado | C11: FOF | D11: 0.08
A12: =B12&"-"&C12 -> Moderado-MULTIESTRATÉGIA | B12: Moderado | C12: MULTIESTRATÉGIA | D12: 0.19
A13: =B13&"-"&C13 -> Moderado-DESENVOLVIMENTO | B13: Moderado | C13: DESENVOLVIMENTO | D13: 0.05
... A19: =B19&"-"&C19 -> Agressivo-DESENVOLVIMENTO | B19: Agressivo | C19: DESENVOLVIMENTO | D19: 0.1
